quizify/__main__.py
quizify/answer.py
quizify/check.py
quizify/presenter.py
quizify/question.py
quizify/quiz.py
quizify-0.1.1.dist-info/METADATA
quizify-0.1.1.dist-info/WHEEL
quizify-0.1.1.dist-info/entry_points.txt
quizify-0.1.1.dist-info/RECORD
