Metadata-Version: 2.1
Name: quizify
Version: 0.1.1
Summary: Quizify is a Python package for creating quizzes from the csv file.
Author: Valijonov
Requires-Python: >=3.10,<4.0
Classifier: Programming Language :: Python :: 3
Classifier: Programming Language :: Python :: 3.10
Classifier: Programming Language :: Python :: 3.11
